loss_checker/__init__.py
loss_checker/__main__.py
loss_checker/client.py
loss_checker/config.py
loss_checker/server.py
loss_checker/cfg/loss_checker.service
loss_checker-0.6.1.dist-info/METADATA
loss_checker-0.6.1.dist-info/WHEEL
loss_checker-0.6.1.dist-info/top_level.txt
loss_checker-0.6.1.dist-info/RECORD
