Metadata-Version: 2.1
Name: loss-checker
Version: 0.6.1
Summary: Loss Checker
Home-page: https://github.com/jok4r/loss_checker
Author: Dmitry Yakovlev
Author-email: opensuse12@gmail.com
License: UNKNOWN
Platform: UNKNOWN
Requires-Python: >=3.5
Requires-Dist: ovcfg
Requires-Dist: oe-common (>=1.3.0)
